MANIFEST.in
README.md
setup.py
lol_scraper/__init__.py
lol_scraper/cassiopeia_proxy.py
lol_scraper/data_types.py
lol_scraper/initialize_configuration.py
lol_scraper/main.py
lol_scraper/match_downloader.py
lol_scraper/summoners_api.py
lol_scraper.egg-info/PKG-INFO
lol_scraper.egg-info/SOURCES.txt
lol_scraper.egg-info/dependency_links.txt
lol_scraper.egg-info/pbr.json
lol_scraper.egg-info/requires.txt
lol_scraper.egg-info/top_level.txt
lol_scraper.egg-info/zip-safe
lol_scraper/concurrency/__init__.py
lol_scraper/concurrency/common.py
lol_scraper/concurrency/process_controller.py
lol_scraper/concurrency/task.py
lol_scraper/concurrency/worker.py
tests/__init__.py
tests/dummy.py
tests/performance.py
tests/tier_test.py