Metadata-Version: 1.1
Name: lol-scraper
Version: 0.2.0
Summary: A python script and library to download and store League of Legends matches with Riot API
Home-page: https://github.com/MakersF/LoLScraper
Author: Francesco Zoffoli
Author-email: makers.f.dev@gmail.com
License: MIT
Keywords: LoL,League of Legends,Riot Games,API,REST
Platform: UNKNOWN
Classifier: Development Status :: 3 - Alpha
Classifier: Programming Language :: Python :: 3
Classifier: Environment :: Web Environment
Classifier: Operating System :: OS Independent
Classifier: Intended Audience :: Developers
Classifier: License :: OSI Approved :: MIT License
Classifier: Topic :: Games/Entertainment
Classifier: Topic :: Games/Entertainment :: Real Time Strategy
Classifier: Topic :: Games/Entertainment :: Role-Playing
Classifier: Topic :: Software Development :: Libraries :: Python Modules
